<?xml version='1.0'?><notes><reading-notes><b>SAMPLE READING NOTES</b><br/>SITUATION: problem at Acme Accounting with tardy junior accountants<br/><br/><u>two possible solutions suggested by senior staff</u>:<br/><dot/>plan 1 (make-up of missed work)<br/><dot/>plan 2 (lose salary for missed work)<br/></reading-notes><listening-notes><b>SAMPLE LISTENING NOTES</b><br/>SITUATION: company president to decide what to do about problem<br/><br/><u>problems with possible solutions</u>:<br/><dot/>plan 1 (not a serious enough penalty but no lost work for 		company)<br/><dot/>plan 2 (a serious penalty but lost work for company)<br/><br/><u>final decision</u>:<br/><dot/>implementation of both plan 1 and plan 2<br/></listening-notes></notes>